{"coord":
    {"lon":-111.25,"lat":42.05},
    "weather":[{"id":803,
    "main":"Clouds",
    "description":"broken clouds",
    "icon":"04d"}],
    "base":"stations",
    "main":{"temp":279.16,"pressure":1019,"humidity":80,"temp_min":274.26,"temp_max":282.59},
    "visibility":16093,"wind":{"speed":1.67,"deg":239},
    "clouds":{"all":75},"dt":1553364096,
    "sys":{"type":1,"id":3981,"message":0.0051,"country":"US","sunrise":1553347400,"sunset":1553391585},
    "id":5585010,
    "name":"Bear Lake Sands",
    "cod":200}